asyncpg_lite/__init__.py
asyncpg_lite-0.22.2.1.dist-info/METADATA
asyncpg_lite-0.22.2.1.dist-info/WHEEL
asyncpg_lite-0.22.2.1.dist-info/top_level.txt
asyncpg_lite-0.22.2.1.dist-info/RECORD
