Metadata-Version: 2.1
Name: asyncpg-lite
Version: 0.22.2.1
Summary: Простая асинхронная библиотека, основанная на asyncpg
Home-page: https://github.com/Yakvenalex/asyncpg_lite
Author: Алексей Яковенко
Author-email: mr.mnogo@gmail.com
Classifier: Programming Language :: Python :: 3
Classifier: License :: OSI Approved :: MIT License
Classifier: Operating System :: OS Independent
Requires-Python: >=3.6
Requires-Dist: asyncpg (>=0.21.0)
